azure/mgmt/monitor/__init__.py
azure/mgmt/monitor/_configuration.py
azure/mgmt/monitor/_monitor_management_client.py
azure/mgmt/monitor/_serialization.py
azure/mgmt/monitor/_version.py
azure/mgmt/monitor/models.py
azure/mgmt/monitor/py.typed
azure/mgmt/monitor/aio/__init__.py
azure/mgmt/monitor/aio/_configuration.py
azure/mgmt/monitor/aio/_monitor_management_client.py
azure/mgmt/monitor/v2015_04_01/__init__.py
azure/mgmt/monitor/v2015_04_01/_configuration.py
azure/mgmt/monitor/v2015_04_01/_monitor_management_client.py
azure/mgmt/monitor/v2015_04_01/_patch.py
azure/mgmt/monitor/v2015_04_01/_vendor.py
azure/mgmt/monitor/v2015_04_01/_version.py
azure/mgmt/monitor/v2015_04_01/aio/__init__.py
azure/mgmt/monitor/v2015_04_01/aio/_configuration.py
azure/mgmt/monitor/v2015_04_01/aio/_monitor_management_client.py
azure/mgmt/monitor/v2015_04_01/aio/_patch.py
azure/mgmt/monitor/v2015_04_01/aio/operations/__init__.py
azure/mgmt/monitor/v2015_04_01/aio/operations/_activity_logs_operations.py
azure/mgmt/monitor/v2015_04_01/aio/operations/_alert_rules_operations.py
azure/mgmt/monitor/v2015_04_01/aio/operations/_autoscale_settings_operations.py
azure/mgmt/monitor/v2015_04_01/aio/operations/_event_categories_operations.py
azure/mgmt/monitor/v2015_04_01/aio/operations/_operations.py
azure/mgmt/monitor/v2015_04_01/aio/operations/_patch.py
azure/mgmt/monitor/v2015_04_01/aio/operations/_tenant_activity_logs_operations.py
azure/mgmt/monitor/v2015_04_01/models/__init__.py
azure/mgmt/monitor/v2015_04_01/models/_models_py3.py
azure/mgmt/monitor/v2015_04_01/models/_monitor_management_client_enums.py
azure/mgmt/monitor/v2015_04_01/models/_patch.py
azure/mgmt/monitor/v2015_04_01/operations/__init__.py
azure/mgmt/monitor/v2015_04_01/operations/_activity_logs_operations.py
azure/mgmt/monitor/v2015_04_01/operations/_alert_rules_operations.py
azure/mgmt/monitor/v2015_04_01/operations/_autoscale_settings_operations.py
azure/mgmt/monitor/v2015_04_01/operations/_event_categories_operations.py
azure_mgmt_monitor-6.0.1.dist-info/LICENSE
azure_mgmt_monitor-6.0.1.dist-info/METADATA
azure_mgmt_monitor-6.0.1.dist-info/WHEEL
azure_mgmt_monitor-6.0.1.dist-info/top_level.txt
azure_mgmt_monitor-6.0.1.dist-info/RECORD
